{"nm":"animacionmedalla 2","ddd":1,"h":500,"w":500,"meta":{"g":"LottieFiles AE 3.0.0"},"layers":[{"ty":3,"nm":"Nulo 2","sr":1,"st":0,"op":1500,"ip":0,"hd":false,"ddd":0,"bm":0,"hasMask":false,"ao":0,"ks":{"a":{"a":0,"k":[0,0,0],"ix":1},"s":{"a":1,"k":[{"o":{"x":0.609,"y":-0.416},"i":{"x":0.667,"y":1},"s":[100,100,100],"t":123},{"s":[0,0,100],"t":145}],"ix":6},"sk":{"a":0,"k":0},"p":{"a":0,"k":[250,250,0],"ix":2},"r":{"a":0,"k":0,"ix":10},"sa":{"a":0,"k":0},"o":{"a":0,"k":0,"ix":11}},"ef":[],"ind":1},{"ty":0,"nm":"Medalla","sr":1,"st":-3,"op":1497,"ip":-3,"hd":false,"ddd":1,"bm":0,"hasMask":false,"ao":0,"ks":{"a":{"a":0,"k":[248,176,0],"ix":1},"s":{"a":1,"k":[{"o":{"x":0.333,"y":0},"i":{"x":0.156,"y":1},"s":[0,0,0],"t":6},{"s":[100,100,100],"t":27}],"ix":6},"sk":{"a":0,"k":0},"p":{"a":0,"k":[-2,-74,0],"ix":2},"sa":{"a":0,"k":0},"o":{"a":0,"k":100,"ix":11},"rx":{"a":1,"k":[{"o":{"x":0.333,"y":0},"i":{"x":0.667,"y":1},"s":[45],"t":6},{"o":{"x":0.333,"y":0},"i":{"x":0.667,"y":1},"s":[-45],"t":20},{"o":{"x":0.333,"y":0},"i":{"x":0.667,"y":1},"s":[15.444],"t":33.837},{"o":{"x":0.333,"y":0},"i":{"x":0.833,"y":1},"s":[-17],"t":45.406},{"o":{"x":0.167,"y":0},"i":{"x":0.833,"y":1},"s":[8],"t":55.047},{"s":[0],"t":63}],"ix":8},"ry":{"a":0,"k":0,"ix":9},"rz":{"a":0,"k":0,"ix":10},"or":{"a":0,"k":[0,0,0],"ix":7}},"ef":[],"w":500,"h":500,"refId":"comp_0","ind":2,"parent":1},{"ty":4,"nm":"Capa de formas 1","sr":1,"st":0,"op":1500,"ip":0,"hd":false,"ddd":0,"bm":0,"hasMask":false,"td":1,"ao":0,"ks":{"a":{"a":0,"k":[16,183.5,0],"ix":1},"s":{"a":0,"k":[100,100,100],"ix":6},"sk":{"a":0,"k":0},"p":{"a":1,"k":[{"o":{"x":0.333,"y":0},"i":{"x":0.199,"y":1},"s":[-16,-386.5,0],"t":0,"ti":[-2.667,-32.5,0],"to":[2.667,32.5,0]},{"s":[0,-191.5,0],"t":18}],"ix":2},"r":{"a":0,"k":0,"ix":10},"sa":{"a":0,"k":0},"o":{"a":0,"k":100,"ix":11}},"ef":[],"shapes":[{"ty":"gr","bm":0,"hd":false,"mn":"ADBE Vector Group","nm":"Rectángulo 1","ix":1,"cix":2,"np":3,"it":[{"ty":"rc","bm":0,"hd":false,"mn":"ADBE Vector Shape - Rect","nm":"Trazado de rectángulo 1","d":1,"p":{"a":0,"k":[0,0],"ix":3},"r":{"a":0,"k":0,"ix":4},"s":{"a":0,"k":[468,329],"ix":2}},{"ty":"fl","bm":0,"hd":false,"mn":"ADBE Vector Graphic - Fill","nm":"Relleno 1","c":{"a":0,"k":[1,1,1],"ix":4},"r":1,"o":{"a":0,"k":100,"ix":5}},{"ty":"tr","a":{"a":0,"k":[0,0],"ix":1},"s":{"a":0,"k":[100,100],"ix":3},"sk":{"a":0,"k":0,"ix":4},"p":{"a":0,"k":[16,183.5],"ix":2},"r":{"a":0,"k":0,"ix":6},"sa":{"a":0,"k":0,"ix":5},"o":{"a":0,"k":100,"ix":7}}]}],"ind":3,"parent":1},{"ty":4,"nm":"Liston adelante contornos","sr":1,"st":0,"op":1500,"ip":0,"hd":false,"ddd":0,"bm":0,"tt":1,"hasMask":false,"ao":0,"ks":{"a":{"a":0,"k":[134.642,134.284,0],"ix":1},"s":{"a":0,"k":[64,64,100],"ix":6},"sk":{"a":0,"k":0},"p":{"a":0,"k":[-57.241,-130.889,0],"ix":2},"r":{"a":0,"k":0,"ix":10},"sa":{"a":0,"k":0},"o":{"a":0,"k":100,"ix":11}},"ef":[],"shapes":[{"ty":"gr","bm":0,"hd":false,"mn":"ADBE Vector Group","nm":"Grupo 1","ix":1,"cix":2,"np":2,"it":[{"ty":"sh","bm":0,"hd":false,"mn":"ADBE Vector Shape - Group","nm":"Trazado 1","ix":1,"d":1,"ks":{"a":0,"k":{"c":true,"i":[[0,0],[0,0],[0,0],[0,0]],"o":[[0,0],[0,0],[0,0],[0,0]],"v":[[-134.392,-134.034],[-38.641,134.034],[134.392,134.034],[38.64,-134.034]]},"ix":2}},{"ty":"fl","bm":0,"hd":false,"mn":"ADBE Vector Graphic - Fill","nm":"Relleno 1","c":{"a":0,"k":[0,0.3294,0.5333],"ix":4},"r":1,"o":{"a":0,"k":100,"ix":5}},{"ty":"tr","a":{"a":0,"k":[0,0],"ix":1},"s":{"a":0,"k":[100,100],"ix":3},"sk":{"a":0,"k":0,"ix":4},"p":{"a":0,"k":[134.642,134.284],"ix":2},"r":{"a":0,"k":0,"ix":6},"sa":{"a":0,"k":0,"ix":5},"o":{"a":0,"k":100,"ix":7}}]}],"ind":4,"parent":1},{"ty":4,"nm":"Capa de formas 2","sr":1,"st":0,"op":1500,"ip":0,"hd":false,"ddd":0,"bm":0,"hasMask":false,"td":1,"ao":0,"ks":{"a":{"a":0,"k":[16,183.5,0],"ix":1},"s":{"a":0,"k":[100,100,100],"ix":6},"sk":{"a":0,"k":0},"p":{"a":1,"k":[{"o":{"x":0.333,"y":0},"i":{"x":0.105,"y":1},"s":[0,-191.5,0],"t":8,"ti":[2.667,32.5,0],"to":[-2.667,-32.5,0]},{"s":[-16,-386.5,0],"t":29}],"ix":2},"r":{"a":0,"k":0,"ix":10},"sa":{"a":0,"k":0},"o":{"a":0,"k":100,"ix":11}},"ef":[],"shapes":[{"ty":"gr","bm":0,"hd":false,"mn":"ADBE Vector Group","nm":"Rectángulo 1","ix":1,"cix":2,"np":3,"it":[{"ty":"rc","bm":0,"hd":false,"mn":"ADBE Vector Shape - Rect","nm":"Trazado de rectángulo 1","d":1,"p":{"a":0,"k":[0,0],"ix":3},"r":{"a":0,"k":0,"ix":4},"s":{"a":0,"k":[468,329],"ix":2}},{"ty":"fl","bm":0,"hd":false,"mn":"ADBE Vector Graphic - Fill","nm":"Relleno 1","c":{"a":0,"k":[1,1,1],"ix":4},"r":1,"o":{"a":0,"k":100,"ix":5}},{"ty":"tr","a":{"a":0,"k":[0,0],"ix":1},"s":{"a":0,"k":[100,100],"ix":3},"sk":{"a":0,"k":0,"ix":4},"p":{"a":0,"k":[16,183.5],"ix":2},"r":{"a":0,"k":0,"ix":6},"sa":{"a":0,"k":0,"ix":5},"o":{"a":0,"k":100,"ix":7}}]}],"ind":5,"parent":1},{"ty":4,"nm":"Liston atras contornos","sr":1,"st":0,"op":1500,"ip":0,"hd":false,"ddd":0,"bm":0,"tt":2,"hasMask":false,"ao":0,"ks":{"a":{"a":0,"k":[135.54,136.799,0],"ix":1},"s":{"a":0,"k":[64,64,100],"ix":6},"sk":{"a":0,"k":0},"p":{"a":0,"k":[45.492,-129.28,0],"ix":2},"r":{"a":0,"k":0,"ix":10},"sa":{"a":0,"k":0},"o":{"a":0,"k":100,"ix":11}},"ef":[],"shapes":[{"ty":"gr","bm":0,"hd":false,"mn":"ADBE Vector Group","nm":"Grupo 1","ix":1,"cix":2,"np":2,"it":[{"ty":"sh","bm":0,"hd":false,"mn":"ADBE Vector Shape - Group","nm":"Trazado 1","ix":1,"d":1,"ks":{"a":0,"k":{"c":true,"i":[[0,0],[0,0],[0,0]],"o":[[0,0],[0,0],[0,0]],"v":[[-58.521,81.918],[58.521,81.918],[0,-81.918]]},"ix":2}},{"ty":"fl","bm":0,"hd":false,"mn":"ADBE Vector Graphic - Fill","nm":"Relleno 1","c":{"a":0,"k":[0,0.1804,0.2941],"ix":4},"r":1,"o":{"a":0,"k":100,"ix":5}},{"ty":"tr","a":{"a":0,"k":[0,0],"ix":1},"s":{"a":0,"k":[100,100],"ix":3},"sk":{"a":0,"k":0,"ix":4},"p":{"a":0,"k":[60.568,186.399],"ix":2},"r":{"a":0,"k":0,"ix":6},"sa":{"a":0,"k":0,"ix":5},"o":{"a":0,"k":100,"ix":7}}]},{"ty":"gr","bm":0,"hd":false,"mn":"ADBE Vector Group","nm":"Grupo 2","ix":2,"cix":2,"np":2,"it":[{"ty":"sh","bm":0,"hd":false,"mn":"ADBE Vector Shape - Group","nm":"Trazado 1","ix":1,"d":1,"ks":{"a":0,"k":{"c":true,"i":[[0,0],[0,0],[0,0],[0,0]],"o":[[0,0],[0,0],[0,0],[0,0]],"v":[[-134.9,131.861],[38.132,131.861],[135.29,-136.549],[-37.742,-136.549]]},"ix":2}},{"ty":"fl","bm":0,"hd":false,"mn":"ADBE Vector Graphic - Fill","nm":"Relleno 1","c":{"a":0,"k":[0,0.3294,0.5333],"ix":4},"r":1,"o":{"a":0,"k":100,"ix":5}},{"ty":"tr","a":{"a":0,"k":[0,0],"ix":1},"s":{"a":0,"k":[100,100],"ix":3},"sk":{"a":0,"k":0,"ix":4},"p":{"a":0,"k":[135.54,136.799],"ix":2},"r":{"a":0,"k":0,"ix":6},"sa":{"a":0,"k":0,"ix":5},"o":{"a":0,"k":100,"ix":7}}]}],"ind":6,"parent":1}],"v":"4.8.0","fr":30,"op":150,"ip":0,"assets":[{"nm":"","id":"comp_0","layers":[{"ty":4,"nm":"Capa de formas 4","sr":1,"st":64,"op":79,"ip":64,"hd":false,"ddd":0,"bm":0,"hasMask":false,"ao":0,"ks":{"a":{"a":0,"k":[-154.5,27.5,0],"ix":1},"s":{"a":1,"k":[{"o":{"x":0.333,"y":0},"i":{"x":0.667,"y":1},"s":[0,0,100],"t":64},{"o":{"x":0.167,"y":0},"i":{"x":0.667,"y":1},"s":[100,100,100],"t":70},{"o":{"x":0.167,"y":0},"i":{"x":0.667,"y":1},"s":[100,100,100],"t":72},{"s":[0,0,100],"t":79}],"ix":6},"sk":{"a":0,"k":0},"p":{"a":0,"k":[156.5,443,0],"ix":2},"r":{"a":0,"k":0,"ix":10},"sa":{"a":0,"k":0},"o":{"a":0,"k":100,"ix":11}},"ef":[],"shapes":[{"ty":"gr","bm":0,"hd":false,"mn":"ADBE Vector Group","nm":"Poliestrella 1","ix":1,"cix":2,"np":3,"it":[{"ty":"sr","bm":0,"hd":false,"mn":"ADBE Vector Shape - Star","nm":"Trazado de poliestrella 1","ix":1,"d":1,"ir":{"a":0,"k":12.502,"ix":6},"is":{"a":0,"k":0,"ix":8},"pt":{"a":0,"k":4,"ix":3},"p":{"a":0,"k":[0,0],"ix":4},"or":{"a":0,"k":25.005,"ix":7},"os":{"a":0,"k":0,"ix":9},"r":{"a":0,"k":0,"ix":5},"sy":1},{"ty":"fl","bm":0,"hd":false,"mn":"ADBE Vector Graphic - Fill","nm":"Relleno 1","c":{"a":0,"k":[0,0.1804,0.2941],"ix":4},"r":1,"o":{"a":0,"k":100,"ix":5}},{"ty":"tr","a":{"a":0,"k":[0,0],"ix":1},"s":{"a":0,"k":[100,100],"ix":3},"sk":{"a":0,"k":0,"ix":4},"p":{"a":0,"k":[-154.5,27.5],"ix":2},"r":{"a":0,"k":0,"ix":6},"sa":{"a":0,"k":0,"ix":5},"o":{"a":0,"k":100,"ix":7}}]}],"ind":1},{"ty":4,"nm":"Capa de formas 3","sr":1,"st":59,"op":74,"ip":59,"hd":false,"ddd":0,"bm":0,"hasMask":false,"ao":0,"ks":{"a":{"a":0,"k":[-154.5,27.5,0],"ix":1},"s":{"a":1,"k":[{"o":{"x":0.333,"y":0},"i":{"x":0.667,"y":1},"s":[0,0,100],"t":59},{"o":{"x":0.167,"y":0},"i":{"x":0.667,"y":1},"s":[100,100,100],"t":65},{"o":{"x":0.167,"y":0},"i":{"x":0.667,"y":1},"s":[100,100,100],"t":67},{"s":[0,0,100],"t":74}],"ix":6},"sk":{"a":0,"k":0},"p":{"a":0,"k":[346.75,200,0],"ix":2},"r":{"a":0,"k":0,"ix":10},"sa":{"a":0,"k":0},"o":{"a":0,"k":100,"ix":11}},"ef":[],"shapes":[{"ty":"gr","bm":0,"hd":false,"mn":"ADBE Vector Group","nm":"Poliestrella 1","ix":1,"cix":2,"np":3,"it":[{"ty":"sr","bm":0,"hd":false,"mn":"ADBE Vector Shape - Star","nm":"Trazado de poliestrella 1","ix":1,"d":1,"ir":{"a":0,"k":12.502,"ix":6},"is":{"a":0,"k":0,"ix":8},"pt":{"a":0,"k":4,"ix":3},"p":{"a":0,"k":[0,0],"ix":4},"or":{"a":0,"k":25.005,"ix":7},"os":{"a":0,"k":0,"ix":9},"r":{"a":0,"k":0,"ix":5},"sy":1},{"ty":"fl","bm":0,"hd":false,"mn":"ADBE Vector Graphic - Fill","nm":"Relleno 1","c":{"a":0,"k":[0,0.1804,0.2941],"ix":4},"r":1,"o":{"a":0,"k":100,"ix":5}},{"ty":"tr","a":{"a":0,"k":[0,0],"ix":1},"s":{"a":0,"k":[100,100],"ix":3},"sk":{"a":0,"k":0,"ix":4},"p":{"a":0,"k":[-154.5,27.5],"ix":2},"r":{"a":0,"k":0,"ix":6},"sa":{"a":0,"k":0,"ix":5},"o":{"a":0,"k":100,"ix":7}}]}],"ind":2},{"ty":4,"nm":"Capa de formas 2","sr":1,"st":53,"op":68,"ip":53,"hd":false,"ddd":0,"bm":0,"hasMask":false,"ao":0,"ks":{"a":{"a":0,"k":[-154.5,27.5,0],"ix":1},"s":{"a":1,"k":[{"o":{"x":0.333,"y":0},"i":{"x":0.667,"y":1},"s":[0,0,100],"t":53},{"o":{"x":0.167,"y":0},"i":{"x":0.667,"y":1},"s":[100,100,100],"t":59},{"o":{"x":0.167,"y":0},"i":{"x":0.667,"y":1},"s":[100,100,100],"t":61},{"s":[0,0,100],"t":68}],"ix":6},"sk":{"a":0,"k":0},"p":{"a":0,"k":[377.25,411.75,0],"ix":2},"r":{"a":0,"k":0,"ix":10},"sa":{"a":0,"k":0},"o":{"a":0,"k":100,"ix":11}},"ef":[],"shapes":[{"ty":"gr","bm":0,"hd":false,"mn":"ADBE Vector Group","nm":"Poliestrella 1","ix":1,"cix":2,"np":3,"it":[{"ty":"sr","bm":0,"hd":false,"mn":"ADBE Vector Shape - Star","nm":"Trazado de poliestrella 1","ix":1,"d":1,"ir":{"a":0,"k":12.502,"ix":6},"is":{"a":0,"k":0,"ix":8},"pt":{"a":0,"k":4,"ix":3},"p":{"a":0,"k":[0,0],"ix":4},"or":{"a":0,"k":25.005,"ix":7},"os":{"a":0,"k":0,"ix":9},"r":{"a":0,"k":0,"ix":5},"sy":1},{"ty":"fl","bm":0,"hd":false,"mn":"ADBE Vector Graphic - Fill","nm":"Relleno 1","c":{"a":0,"k":[0,0.1804,0.2941],"ix":4},"r":1,"o":{"a":0,"k":100,"ix":5}},{"ty":"tr","a":{"a":0,"k":[0,0],"ix":1},"s":{"a":0,"k":[100,100],"ix":3},"sk":{"a":0,"k":0,"ix":4},"p":{"a":0,"k":[-154.5,27.5],"ix":2},"r":{"a":0,"k":0,"ix":6},"sa":{"a":0,"k":0,"ix":5},"o":{"a":0,"k":100,"ix":7}}]}],"ind":3},{"ty":4,"nm":"Capa de formas 1","sr":1,"st":48,"op":63,"ip":48,"hd":false,"ddd":0,"bm":0,"hasMask":false,"ao":0,"ks":{"a":{"a":0,"k":[-154.5,27.5,0],"ix":1},"s":{"a":1,"k":[{"o":{"x":0.333,"y":0},"i":{"x":0.667,"y":1},"s":[0,0,100],"t":48},{"o":{"x":0.167,"y":0},"i":{"x":0.667,"y":1},"s":[100,100,100],"t":54},{"o":{"x":0.167,"y":0},"i":{"x":0.667,"y":1},"s":[100,100,100],"t":56},{"s":[0,0,100],"t":63}],"ix":6},"sk":{"a":0,"k":0},"p":{"a":0,"k":[125.75,232.25,0],"ix":2},"r":{"a":0,"k":0,"ix":10},"sa":{"a":0,"k":0},"o":{"a":0,"k":100,"ix":11}},"ef":[],"shapes":[{"ty":"gr","bm":0,"hd":false,"mn":"ADBE Vector Group","nm":"Poliestrella 1","ix":1,"cix":2,"np":3,"it":[{"ty":"sr","bm":0,"hd":false,"mn":"ADBE Vector Shape - Star","nm":"Trazado de poliestrella 1","ix":1,"d":1,"ir":{"a":0,"k":12.502,"ix":6},"is":{"a":0,"k":0,"ix":8},"pt":{"a":0,"k":4,"ix":3},"p":{"a":0,"k":[0,0],"ix":4},"or":{"a":0,"k":25.005,"ix":7},"os":{"a":0,"k":0,"ix":9},"r":{"a":0,"k":0,"ix":5},"sy":1},{"ty":"fl","bm":0,"hd":false,"mn":"ADBE Vector Graphic - Fill","nm":"Relleno 1","c":{"a":0,"k":[0,0.1804,0.2941],"ix":4},"r":1,"o":{"a":0,"k":100,"ix":5}},{"ty":"tr","a":{"a":0,"k":[0,0],"ix":1},"s":{"a":0,"k":[100,100],"ix":3},"sk":{"a":0,"k":0,"ix":4},"p":{"a":0,"k":[-154.5,27.5],"ix":2},"r":{"a":0,"k":0,"ix":6},"sa":{"a":0,"k":0,"ix":5},"o":{"a":0,"k":100,"ix":7}}]}],"ind":4},{"ty":0,"nm":"estrella","sr":1,"st":15,"op":1515,"ip":15,"hd":false,"ddd":0,"bm":0,"hasMask":false,"ao":0,"ks":{"a":{"a":0,"k":[252,323.5,0],"ix":1},"s":{"a":1,"k":[{"o":{"x":0.333,"y":0},"i":{"x":0,"y":1},"s":[0,0,100],"t":15},{"s":[100,100,100],"t":38}],"ix":6},"sk":{"a":0,"k":0},"p":{"a":0,"k":[252,323.5,0],"ix":2},"r":{"a":1,"k":[{"o":{"x":0.333,"y":0},"i":{"x":0,"y":1},"s":[-90],"t":15},{"s":[0],"t":38}],"ix":10},"sa":{"a":0,"k":0},"o":{"a":0,"k":100,"ix":11}},"ef":[],"w":500,"h":500,"refId":"comp_1","ind":5},{"ty":4,"nm":"Fondo linea contornos 2","sr":1,"st":0,"op":1500,"ip":0,"hd":false,"ddd":0,"bm":0,"hasMask":false,"td":1,"ao":0,"ks":{"a":{"a":0,"k":[265.054,256.838,0],"ix":1},"s":{"a":0,"k":[64,64,100],"ix":6},"sk":{"a":0,"k":0},"p":{"a":0,"k":[250.959,316.267,0],"ix":2},"r":{"a":0,"k":0,"ix":10},"sa":{"a":0,"k":0},"o":{"a":0,"k":100,"ix":11}},"ef":[],"shapes":[{"ty":"gr","bm":0,"hd":false,"mn":"ADBE Vector Group","nm":"Grupo 1","ix":1,"cix":2,"np":2,"it":[{"ty":"sh","bm":0,"hd":false,"mn":"ADBE Vector Shape - Group","nm":"Trazado 1","ix":1,"d":1,"ks":{"a":0,"k":{"c":false,"i":[[0,0],[41.057,41.056],[-79.576,79.576],[-79.576,-79.576],[44.186,-77.754]],"o":[[-53.798,1.309],[-79.576,-79.576],[79.576,-79.576],[66.303,66.303],[0,0]],"v":[[6.094,213.029],[-142.978,153.408],[-142.978,-134.762],[145.192,-134.762],[178.368,109.923]]},"ix":2}},{"ty":"st","bm":0,"hd":false,"mn":"ADBE Vector Graphic - Stroke","nm":"Trazo 1","lc":2,"lj":2,"ml":1,"o":{"a":0,"k":100,"ix":4},"w":{"a":0,"k":17,"ix":5},"c":{"a":0,"k":[0.8588,0.5412,0.1569],"ix":3}},{"ty":"tr","a":{"a":0,"k":[0,0],"ix":1},"s":{"a":0,"k":[100,100],"ix":3},"sk":{"a":0,"k":0,"ix":4},"p":{"a":0,"k":[265.054,256.838],"ix":2},"r":{"a":0,"k":0,"ix":6},"sa":{"a":0,"k":0,"ix":5},"o":{"a":0,"k":100,"ix":7}}]},{"ty":"gr","bm":0,"hd":false,"mn":"ADBE Vector Group","nm":"Grupo 2","ix":2,"cix":2,"np":2,"it":[{"ty":"sh","bm":0,"hd":false,"mn":"ADBE Vector Shape - Group","nm":"Trazado 1","ix":1,"d":1,"ks":{"a":0,"k":{"c":false,"i":[[0,0],[5.713,-5.713],[4.831,-4.014]],"o":[[-4.893,6.186],[-4.528,4.529],[0,0]],"v":[[14.979,-15.34],[-0.93,2.527],[-14.979,15.34]]},"ix":2}},{"ty":"st","bm":0,"hd":false,"mn":"ADBE Vector Graphic - Stroke","nm":"Trazo 1","lc":2,"lj":2,"ml":1,"o":{"a":0,"k":100,"ix":4},"w":{"a":0,"k":17,"ix":5},"c":{"a":0,"k":[0.8588,0.5412,0.1569],"ix":3}},{"ty":"tr","a":{"a":0,"k":[0,0],"ix":1},"s":{"a":0,"k":[100,100],"ix":3},"sk":{"a":0,"k":0,"ix":4},"p":{"a":0,"k":[411.176,407.719],"ix":2},"r":{"a":0,"k":0,"ix":6},"sa":{"a":0,"k":0,"ix":5},"o":{"a":0,"k":100,"ix":7}}]}],"ind":6},{"ty":4,"nm":"destello 4","sr":1,"st":0,"op":1500,"ip":0,"hd":false,"ddd":0,"bm":0,"tt":1,"hasMask":false,"ao":0,"ks":{"a":{"a":0,"k":[-62,125,0],"ix":1},"s":{"a":0,"k":[64,64,100],"ix":6},"sk":{"a":0,"k":0},"p":{"a":1,"k":[{"o":{"x":0.333,"y":0},"i":{"x":0.667,"y":1},"s":[103.6,172.96,0],"t":25,"ti":[-49.707,-49.92,0],"to":[49.707,49.92,0]},{"s":[401.84,472.48,0],"t":55}],"ix":2},"r":{"a":0,"k":45,"ix":10},"sa":{"a":0,"k":0},"o":{"a":0,"k":68,"ix":11}},"ef":[],"shapes":[{"ty":"gr","bm":0,"hd":false,"mn":"ADBE Vector Group","nm":"Rectángulo 1","ix":1,"cix":2,"np":3,"it":[{"ty":"rc","bm":0,"hd":false,"mn":"ADBE Vector Shape - Rect","nm":"Trazado de rectángulo 1","d":1,"p":{"a":0,"k":[0,0],"ix":3},"r":{"a":0,"k":0,"ix":4},"s":{"a":0,"k":[136,706],"ix":2}},{"ty":"fl","bm":0,"hd":false,"mn":"ADBE Vector Graphic - Fill","nm":"Relleno 1","c":{"a":0,"k":[1,1,1],"ix":4},"r":1,"o":{"a":0,"k":100,"ix":5}},{"ty":"tr","a":{"a":0,"k":[0,0],"ix":1},"s":{"a":0,"k":[100,100],"ix":3},"sk":{"a":0,"k":0,"ix":4},"p":{"a":0,"k":[-62,125],"ix":2},"r":{"a":0,"k":0,"ix":6},"sa":{"a":0,"k":0,"ix":5},"o":{"a":0,"k":100,"ix":7}}]}],"ind":7},{"ty":4,"nm":"Fondo linea contornos","sr":1,"st":0,"op":1500,"ip":0,"hd":false,"ddd":0,"bm":0,"hasMask":false,"ao":0,"ks":{"a":{"a":0,"k":[265.054,256.838,0],"ix":1},"s":{"a":0,"k":[64,64,100],"ix":6},"sk":{"a":0,"k":0},"p":{"a":0,"k":[250.959,316.267,0],"ix":2},"r":{"a":0,"k":0,"ix":10},"sa":{"a":0,"k":0},"o":{"a":0,"k":100,"ix":11}},"ef":[],"shapes":[{"ty":"gr","bm":0,"hd":false,"mn":"ADBE Vector Group","nm":"Grupo 1","ix":1,"cix":2,"np":2,"it":[{"ty":"sh","bm":0,"hd":false,"mn":"ADBE Vector Shape - Group","nm":"Trazado 1","ix":1,"d":1,"ks":{"a":0,"k":{"c":false,"i":[[0,0],[41.057,41.056],[-79.576,79.576],[-79.576,-79.576],[44.186,-77.754]],"o":[[-53.798,1.309],[-79.576,-79.576],[79.576,-79.576],[66.303,66.303],[0,0]],"v":[[6.094,213.029],[-142.978,153.408],[-142.978,-134.762],[145.192,-134.762],[178.368,109.923]]},"ix":2}},{"ty":"st","bm":0,"hd":false,"mn":"ADBE Vector Graphic - Stroke","nm":"Trazo 1","lc":2,"lj":2,"ml":1,"o":{"a":0,"k":100,"ix":4},"w":{"a":0,"k":17,"ix":5},"c":{"a":0,"k":[0.6745,0.4275,0.1255],"ix":3}},{"ty":"tr","a":{"a":0,"k":[0,0],"ix":1},"s":{"a":0,"k":[100,100],"ix":3},"sk":{"a":0,"k":0,"ix":4},"p":{"a":0,"k":[265.054,256.838],"ix":2},"r":{"a":0,"k":0,"ix":6},"sa":{"a":0,"k":0,"ix":5},"o":{"a":0,"k":100,"ix":7}}]},{"ty":"gr","bm":0,"hd":false,"mn":"ADBE Vector Group","nm":"Grupo 2","ix":2,"cix":2,"np":2,"it":[{"ty":"sh","bm":0,"hd":false,"mn":"ADBE Vector Shape - Group","nm":"Trazado 1","ix":1,"d":1,"ks":{"a":0,"k":{"c":false,"i":[[0,0],[5.713,-5.713],[4.831,-4.014]],"o":[[-4.893,6.186],[-4.528,4.529],[0,0]],"v":[[14.979,-15.34],[-0.93,2.527],[-14.979,15.34]]},"ix":2}},{"ty":"st","bm":0,"hd":false,"mn":"ADBE Vector Graphic - Stroke","nm":"Trazo 1","lc":2,"lj":2,"ml":1,"o":{"a":0,"k":100,"ix":4},"w":{"a":0,"k":17,"ix":5},"c":{"a":0,"k":[0.6745,0.4275,0.1255],"ix":3}},{"ty":"tr","a":{"a":0,"k":[0,0],"ix":1},"s":{"a":0,"k":[100,100],"ix":3},"sk":{"a":0,"k":0,"ix":4},"p":{"a":0,"k":[411.176,407.719],"ix":2},"r":{"a":0,"k":0,"ix":6},"sa":{"a":0,"k":0,"ix":5},"o":{"a":0,"k":100,"ix":7}}]}],"ind":8},{"ty":4,"nm":"Fondo 1 mate","sr":1,"st":0,"op":1500,"ip":0,"hd":false,"ddd":0,"bm":0,"hasMask":false,"td":1,"ao":0,"ks":{"a":{"a":0,"k":[264.107,264.107,0],"ix":1},"s":{"a":0,"k":[64,64,100],"ix":6},"sk":{"a":0,"k":0},"p":{"a":0,"k":[251.667,322.233,0],"ix":2},"r":{"a":0,"k":0,"ix":10},"sa":{"a":0,"k":0},"o":{"a":0,"k":100,"ix":11}},"ef":[],"shapes":[{"ty":"gr","bm":0,"hd":false,"mn":"ADBE Vector Group","nm":"Grupo 1","ix":1,"cix":2,"np":2,"it":[{"ty":"sh","bm":0,"hd":false,"mn":"ADBE Vector Shape - Group","nm":"Trazado 1","ix":1,"d":1,"ks":{"a":0,"k":{"c":true,"i":[[-93.877,93.877],[-93.877,-93.877],[93.877,-93.877],[93.877,93.877]],"o":[[93.877,-93.877],[93.877,93.877],[-93.877,93.877],[-93.877,-93.877]],"v":[[-169.979,-169.98],[169.98,-169.98],[169.98,169.98],[-169.979,169.98]]},"ix":2}},{"ty":"fl","bm":0,"hd":false,"mn":"ADBE Vector Graphic - Fill","nm":"Relleno 1","c":{"a":0,"k":[0.8588,0.5412,0.1569],"ix":4},"r":1,"o":{"a":0,"k":100,"ix":5}},{"ty":"tr","a":{"a":0,"k":[0,0],"ix":1},"s":{"a":0,"k":[100,100],"ix":3},"sk":{"a":0,"k":0,"ix":4},"p":{"a":0,"k":[264.106,264.106],"ix":2},"r":{"a":0,"k":0,"ix":6},"sa":{"a":0,"k":0,"ix":5},"o":{"a":0,"k":100,"ix":7}}]}],"ind":9},{"ty":4,"nm":"destello","sr":1,"st":0,"op":1500,"ip":0,"hd":false,"ddd":0,"bm":0,"tt":1,"hasMask":false,"ao":0,"ks":{"a":{"a":0,"k":[-62,125,0],"ix":1},"s":{"a":0,"k":[64,64,100],"ix":6},"sk":{"a":0,"k":0},"p":{"a":1,"k":[{"o":{"x":0.333,"y":0},"i":{"x":0.667,"y":1},"s":[103.6,172.96,0],"t":21,"ti":[-49.707,-49.92,0],"to":[49.707,49.92,0]},{"s":[401.84,472.48,0],"t":51}],"ix":2},"r":{"a":0,"k":45,"ix":10},"sa":{"a":0,"k":0},"o":{"a":0,"k":68,"ix":11}},"ef":[],"shapes":[{"ty":"gr","bm":0,"hd":false,"mn":"ADBE Vector Group","nm":"Rectángulo 1","ix":1,"cix":2,"np":3,"it":[{"ty":"rc","bm":0,"hd":false,"mn":"ADBE Vector Shape - Rect","nm":"Trazado de rectángulo 1","d":1,"p":{"a":0,"k":[0,0],"ix":3},"r":{"a":0,"k":0,"ix":4},"s":{"a":0,"k":[136,706],"ix":2}},{"ty":"fl","bm":0,"hd":false,"mn":"ADBE Vector Graphic - Fill","nm":"Relleno 1","c":{"a":0,"k":[1,1,1],"ix":4},"r":1,"o":{"a":0,"k":100,"ix":5}},{"ty":"tr","a":{"a":0,"k":[0,0],"ix":1},"s":{"a":0,"k":[100,100],"ix":3},"sk":{"a":0,"k":0,"ix":4},"p":{"a":0,"k":[-62,125],"ix":2},"r":{"a":0,"k":0,"ix":6},"sa":{"a":0,"k":0,"ix":5},"o":{"a":0,"k":100,"ix":7}}]}],"ind":10},{"ty":4,"nm":"Fondo 1 contornos 2","sr":1,"st":0,"op":1500,"ip":0,"hd":false,"ddd":0,"bm":0,"hasMask":false,"ao":0,"ks":{"a":{"a":0,"k":[264.107,264.107,0],"ix":1},"s":{"a":0,"k":[64,64,100],"ix":6},"sk":{"a":0,"k":0},"p":{"a":0,"k":[251.667,322.233,0],"ix":2},"r":{"a":0,"k":0,"ix":10},"sa":{"a":0,"k":0},"o":{"a":0,"k":100,"ix":11}},"ef":[],"shapes":[{"ty":"gr","bm":0,"hd":false,"mn":"ADBE Vector Group","nm":"Grupo 1","ix":1,"cix":2,"np":2,"it":[{"ty":"sh","bm":0,"hd":false,"mn":"ADBE Vector Shape - Group","nm":"Trazado 1","ix":1,"d":1,"ks":{"a":0,"k":{"c":true,"i":[[-93.877,93.877],[-93.877,-93.877],[93.877,-93.877],[93.877,93.877]],"o":[[93.877,-93.877],[93.877,93.877],[-93.877,93.877],[-93.877,-93.877]],"v":[[-169.979,-169.98],[169.98,-169.98],[169.98,169.98],[-169.979,169.98]]},"ix":2}},{"ty":"fl","bm":0,"hd":false,"mn":"ADBE Vector Graphic - Fill","nm":"Relleno 1","c":{"a":0,"k":[0.8588,0.5412,0.1569],"ix":4},"r":1,"o":{"a":0,"k":100,"ix":5}},{"ty":"tr","a":{"a":0,"k":[0,0],"ix":1},"s":{"a":0,"k":[100,100],"ix":3},"sk":{"a":0,"k":0,"ix":4},"p":{"a":0,"k":[264.106,264.106],"ix":2},"r":{"a":0,"k":0,"ix":6},"sa":{"a":0,"k":0,"ix":5},"o":{"a":0,"k":100,"ix":7}}]}],"ind":11},{"ty":4,"nm":"Fondo 1 contornos","sr":1,"st":0,"op":58,"ip":0,"hd":false,"ddd":0,"bm":0,"hasMask":false,"ao":0,"ks":{"a":{"a":0,"k":[264.107,264.107,0],"ix":1},"s":{"a":0,"k":[64,64,100],"ix":6},"sk":{"a":0,"k":0},"p":{"a":1,"k":[{"o":{"x":0.333,"y":0},"i":{"x":0.667,"y":1},"s":[251.667,315.233,0],"t":13,"ti":[0,0.5,0],"to":[0,5,0]},{"o":{"x":0.333,"y":0},"i":{"x":0.667,"y":1},"s":[251.667,345.233,0],"t":23,"ti":[0,2.25,0],"to":[0,-0.5,0]},{"o":{"x":0.333,"y":0},"i":{"x":0.667,"y":1},"s":[251.667,312.233,0],"t":37,"ti":[0,-1.5,0],"to":[0,-2.25,0]},{"o":{"x":0.333,"y":0},"i":{"x":0.667,"y":1},"s":[251.667,331.733,0],"t":48,"ti":[0,1.75,0],"to":[0,1.5,0]},{"s":[251.667,321.233,0],"t":58}],"ix":2},"r":{"a":0,"k":0,"ix":10},"sa":{"a":0,"k":0},"o":{"a":0,"k":100,"ix":11}},"ef":[],"shapes":[{"ty":"gr","bm":0,"hd":false,"mn":"ADBE Vector Group","nm":"Grupo 1","ix":1,"cix":2,"np":2,"it":[{"ty":"sh","bm":0,"hd":false,"mn":"ADBE Vector Shape - Group","nm":"Trazado 1","ix":1,"d":1,"ks":{"a":0,"k":{"c":true,"i":[[-93.877,93.877],[-93.877,-93.877],[93.877,-93.877],[93.877,93.877]],"o":[[93.877,-93.877],[93.877,93.877],[-93.877,93.877],[-93.877,-93.877]],"v":[[-169.979,-169.98],[169.98,-169.98],[169.98,169.98],[-169.979,169.98]]},"ix":2}},{"ty":"fl","bm":0,"hd":false,"mn":"ADBE Vector Graphic - Fill","nm":"Relleno 1","c":{"a":0,"k":[0.6745,0.4353,0.102],"ix":4},"r":1,"o":{"a":0,"k":100,"ix":5}},{"ty":"tr","a":{"a":0,"k":[0,0],"ix":1},"s":{"a":0,"k":[100,100],"ix":3},"sk":{"a":0,"k":0,"ix":4},"p":{"a":0,"k":[264.106,264.106],"ix":2},"r":{"a":0,"k":0,"ix":6},"sa":{"a":0,"k":0,"ix":5},"o":{"a":0,"k":100,"ix":7}}]}],"ind":12}]},{"nm":"","id":"comp_1","layers":[{"ty":4,"nm":"estrella linea contornos","sr":1,"st":0,"op":1500,"ip":0,"hd":false,"ddd":0,"bm":0,"hasMask":false,"td":1,"ao":0,"ks":{"a":{"a":0,"k":[159.204,153.492,0],"ix":1},"s":{"a":0,"k":[64,64,100],"ix":6},"sk":{"a":0,"k":0},"p":{"a":0,"k":[251.667,318.426,0],"ix":2},"r":{"a":0,"k":0,"ix":10},"sa":{"a":0,"k":0},"o":{"a":0,"k":100,"ix":11}},"ef":[],"shapes":[{"ty":"gr","bm":0,"hd":false,"mn":"ADBE Vector Group","nm":"Grupo 1","ix":1,"cix":2,"np":2,"it":[{"ty":"sh","bm":0,"hd":false,"mn":"ADBE Vector Shape - Group","nm":"Trazado 1","ix":1,"d":1,"ks":{"a":0,"k":{"c":false,"i":[[0,0],[0,0]],"o":[[0,0],[0,0]],"v":[[1.884,-10.981],[-1.884,10.981]]},"ix":2}},{"ty":"st","bm":0,"hd":false,"mn":"ADBE Vector Graphic - Stroke","nm":"Trazo 1","lc":2,"lj":2,"ml":1,"o":{"a":0,"k":100,"ix":4},"w":{"a":0,"k":17,"ix":5},"c":{"a":0,"k":[0.6745,0.4275,0.1255],"ix":3}},{"ty":"tr","a":{"a":0,"k":[0,0],"ix":1},"s":{"a":0,"k":[100,100],"ix":3},"sk":{"a":0,"k":0,"ix":4},"p":{"a":0,"k":[91.118,229.427],"ix":2},"r":{"a":0,"k":0,"ix":6},"sa":{"a":0,"k":0,"ix":5},"o":{"a":0,"k":100,"ix":7}}]},{"ty":"gr","bm":0,"hd":false,"mn":"ADBE Vector Group","nm":"Grupo 2","ix":2,"cix":2,"np":2,"it":[{"ty":"sh","bm":0,"hd":false,"mn":"ADBE Vector Shape - Group","nm":"Trazado 1","ix":1,"d":1,"ks":{"a":0,"k":{"c":false,"i":[[0,0],[0,0],[-3.329,1.75],[0,0],[-1.323,-0.695],[0,0],[0.636,3.707],[0,0],[-1.07,1.043],[0,0],[3.722,0.541],[0,0],[0.661,1.34],[0,0],[1.665,-3.372],[0,0],[1.478,-0.215],[0,0],[-2.693,-2.625],[0,0]],"o":[[0,0],[-0.635,3.707],[0,0],[1.322,-0.695],[0,0],[3.329,1.75],[0,0],[-0.252,-1.472],[0,0],[2.694,-2.625],[0,0],[-1.478,-0.215],[0,0],[-1.664,-3.372],[0,0],[-0.661,1.34],[0,0],[-3.722,0.541],[0,0],[0,0]],"v":[[-69.969,86.916],[-72.978,104.457],[-66.393,109.241],[-2.112,75.447],[2.112,75.447],[66.393,109.241],[72.977,104.457],[60.7,32.879],[62.006,28.862],[114.01,-21.83],[111.495,-29.57],[39.627,-40.013],[36.21,-42.496],[4.069,-107.619],[-4.07,-107.619],[-36.21,-42.496],[-39.627,-40.013],[-111.496,-29.57],[-114.011,-21.83],[-62.006,28.862]]},"ix":2}},{"ty":"st","bm":0,"hd":false,"mn":"ADBE Vector Graphic - Stroke","nm":"Trazo 1","lc":2,"lj":2,"ml":1,"o":{"a":0,"k":100,"ix":4},"w":{"a":0,"k":17,"ix":5},"c":{"a":0,"k":[0.6745,0.4275,0.1255],"ix":3}},{"ty":"tr","a":{"a":0,"k":[0,0],"ix":1},"s":{"a":0,"k":[100,100],"ix":3},"sk":{"a":0,"k":0,"ix":4},"p":{"a":0,"k":[159.204,153.492],"ix":2},"r":{"a":0,"k":0,"ix":6},"sa":{"a":0,"k":0,"ix":5},"o":{"a":0,"k":100,"ix":7}}]}],"ind":1},{"ty":4,"nm":"destello 2","sr":1,"st":0,"op":1500,"ip":0,"hd":false,"ddd":0,"bm":0,"tt":1,"hasMask":false,"ao":0,"ks":{"a":{"a":0,"k":[-62,125,0],"ix":1},"s":{"a":0,"k":[64,64,100],"ix":6},"sk":{"a":0,"k":0},"p":{"a":1,"k":[{"o":{"x":0.333,"y":0},"i":{"x":0.667,"y":1},"s":[103.6,172.96,0],"t":11,"ti":[-49.707,-49.92,0],"to":[49.707,49.92,0]},{"s":[401.84,472.48,0],"t":41}],"ix":2},"r":{"a":0,"k":45,"ix":10},"sa":{"a":0,"k":0},"o":{"a":0,"k":68,"ix":11}},"ef":[],"shapes":[{"ty":"gr","bm":0,"hd":false,"mn":"ADBE Vector Group","nm":"Rectángulo 1","ix":1,"cix":2,"np":3,"it":[{"ty":"rc","bm":0,"hd":false,"mn":"ADBE Vector Shape - Rect","nm":"Trazado de rectángulo 1","d":1,"p":{"a":0,"k":[0,0],"ix":3},"r":{"a":0,"k":0,"ix":4},"s":{"a":0,"k":[136,706],"ix":2}},{"ty":"fl","bm":0,"hd":false,"mn":"ADBE Vector Graphic - Fill","nm":"Relleno 1","c":{"a":0,"k":[1,1,1],"ix":4},"r":1,"o":{"a":0,"k":100,"ix":5}},{"ty":"tr","a":{"a":0,"k":[0,0],"ix":1},"s":{"a":0,"k":[100,100],"ix":3},"sk":{"a":0,"k":0,"ix":4},"p":{"a":0,"k":[-62,125],"ix":2},"r":{"a":0,"k":0,"ix":6},"sa":{"a":0,"k":0,"ix":5},"o":{"a":0,"k":100,"ix":7}}]}],"ind":2},{"ty":4,"nm":"estrella linea contornos 3","sr":1,"st":0,"op":1500,"ip":0,"hd":false,"ddd":0,"bm":0,"hasMask":false,"ao":0,"ks":{"a":{"a":0,"k":[159.204,153.492,0],"ix":1},"s":{"a":0,"k":[64,64,100],"ix":6},"sk":{"a":0,"k":0},"p":{"a":0,"k":[251.667,318.426,0],"ix":2},"r":{"a":0,"k":0,"ix":10},"sa":{"a":0,"k":0},"o":{"a":0,"k":100,"ix":11}},"ef":[],"shapes":[{"ty":"gr","bm":0,"hd":false,"mn":"ADBE Vector Group","nm":"Grupo 1","ix":1,"cix":2,"np":2,"it":[{"ty":"sh","bm":0,"hd":false,"mn":"ADBE Vector Shape - Group","nm":"Trazado 1","ix":1,"d":1,"ks":{"a":0,"k":{"c":false,"i":[[0,0],[0,0]],"o":[[0,0],[0,0]],"v":[[1.884,-10.981],[-1.884,10.981]]},"ix":2}},{"ty":"st","bm":0,"hd":false,"mn":"ADBE Vector Graphic - Stroke","nm":"Trazo 1","lc":2,"lj":2,"ml":1,"o":{"a":0,"k":100,"ix":4},"w":{"a":0,"k":17,"ix":5},"c":{"a":0,"k":[0.6745,0.4275,0.1255],"ix":3}},{"ty":"tr","a":{"a":0,"k":[0,0],"ix":1},"s":{"a":0,"k":[100,100],"ix":3},"sk":{"a":0,"k":0,"ix":4},"p":{"a":0,"k":[91.118,229.427],"ix":2},"r":{"a":0,"k":0,"ix":6},"sa":{"a":0,"k":0,"ix":5},"o":{"a":0,"k":100,"ix":7}}]},{"ty":"gr","bm":0,"hd":false,"mn":"ADBE Vector Group","nm":"Grupo 2","ix":2,"cix":2,"np":2,"it":[{"ty":"sh","bm":0,"hd":false,"mn":"ADBE Vector Shape - Group","nm":"Trazado 1","ix":1,"d":1,"ks":{"a":0,"k":{"c":false,"i":[[0,0],[0,0],[-3.329,1.75],[0,0],[-1.323,-0.695],[0,0],[0.636,3.707],[0,0],[-1.07,1.043],[0,0],[3.722,0.541],[0,0],[0.661,1.34],[0,0],[1.665,-3.372],[0,0],[1.478,-0.215],[0,0],[-2.693,-2.625],[0,0]],"o":[[0,0],[-0.635,3.707],[0,0],[1.322,-0.695],[0,0],[3.329,1.75],[0,0],[-0.252,-1.472],[0,0],[2.694,-2.625],[0,0],[-1.478,-0.215],[0,0],[-1.664,-3.372],[0,0],[-0.661,1.34],[0,0],[-3.722,0.541],[0,0],[0,0]],"v":[[-69.969,86.916],[-72.978,104.457],[-66.393,109.241],[-2.112,75.447],[2.112,75.447],[66.393,109.241],[72.977,104.457],[60.7,32.879],[62.006,28.862],[114.01,-21.83],[111.495,-29.57],[39.627,-40.013],[36.21,-42.496],[4.069,-107.619],[-4.07,-107.619],[-36.21,-42.496],[-39.627,-40.013],[-111.496,-29.57],[-114.011,-21.83],[-62.006,28.862]]},"ix":2}},{"ty":"st","bm":0,"hd":false,"mn":"ADBE Vector Graphic - Stroke","nm":"Trazo 1","lc":2,"lj":2,"ml":1,"o":{"a":0,"k":100,"ix":4},"w":{"a":0,"k":17,"ix":5},"c":{"a":0,"k":[0.6745,0.4275,0.1255],"ix":3}},{"ty":"tr","a":{"a":0,"k":[0,0],"ix":1},"s":{"a":0,"k":[100,100],"ix":3},"sk":{"a":0,"k":0,"ix":4},"p":{"a":0,"k":[159.204,153.492],"ix":2},"r":{"a":0,"k":0,"ix":6},"sa":{"a":0,"k":0,"ix":5},"o":{"a":0,"k":100,"ix":7}}]}],"ind":3},{"ty":4,"nm":"estrella contornos 2","sr":1,"st":0,"op":1500,"ip":0,"hd":false,"ddd":0,"bm":0,"hasMask":false,"td":1,"ao":0,"ks":{"a":{"a":0,"k":[116.953,111.242,0],"ix":1},"s":{"a":0,"k":[64,64,100],"ix":6},"sk":{"a":0,"k":0},"p":{"a":0,"k":[251.667,318.426,0],"ix":2},"r":{"a":0,"k":0,"ix":10},"sa":{"a":0,"k":0},"o":{"a":0,"k":100,"ix":11}},"ef":[],"shapes":[{"ty":"gr","bm":0,"hd":false,"mn":"ADBE Vector Group","nm":"Grupo 1","ix":1,"cix":2,"np":2,"it":[{"ty":"sh","bm":0,"hd":false,"mn":"ADBE Vector Shape - Group","nm":"Trazado 1","ix":1,"d":1,"ks":{"a":0,"k":{"c":true,"i":[[1.665,-3.373],[0,0],[1.478,-0.214],[0,0],[-2.693,-2.625],[0,0],[0.252,-1.472],[0,0],[-3.329,1.75],[0,0],[-1.322,-0.695],[0,0],[0.636,3.707],[0,0],[-1.069,1.043],[0,0],[3.722,0.54],[0,0],[0.661,1.339],[0,0]],"o":[[0,0],[-0.661,1.339],[0,0],[-3.722,0.54],[0,0],[1.069,1.043],[0,0],[-0.636,3.707],[0,0],[1.322,-0.695],[0,0],[3.33,1.75],[0,0],[-0.252,-1.472],[0,0],[2.693,-2.625],[0,0],[-1.478,-0.214],[0,0],[-1.665,-3.373]],"v":[[-4.069,-107.619],[-36.211,-42.495],[-39.626,-40.013],[-111.495,-29.569],[-114.01,-21.829],[-62.005,28.863],[-60.701,32.88],[-72.977,104.458],[-66.393,109.242],[-2.112,75.447],[2.112,75.447],[66.393,109.242],[72.978,104.458],[60.701,32.88],[62.005,28.863],[114.01,-21.829],[111.495,-29.569],[39.627,-40.013],[36.21,-42.495],[4.07,-107.619]]},"ix":2}},{"ty":"fl","bm":0,"hd":false,"mn":"ADBE Vector Graphic - Fill","nm":"Relleno 1","c":{"a":0,"k":[0.8588,0.5412,0.1569],"ix":4},"r":1,"o":{"a":0,"k":100,"ix":5}},{"ty":"tr","a":{"a":0,"k":[0,0],"ix":1},"s":{"a":0,"k":[100,100],"ix":3},"sk":{"a":0,"k":0,"ix":4},"p":{"a":0,"k":[116.953,111.242],"ix":2},"r":{"a":0,"k":0,"ix":6},"sa":{"a":0,"k":0,"ix":5},"o":{"a":0,"k":100,"ix":7}}]}],"ind":4},{"ty":4,"nm":"destello 3","sr":1,"st":0,"op":1500,"ip":0,"hd":false,"ddd":0,"bm":0,"tt":1,"hasMask":false,"ao":0,"ks":{"a":{"a":0,"k":[-62,125,0],"ix":1},"s":{"a":0,"k":[64,64,100],"ix":6},"sk":{"a":0,"k":0},"p":{"a":1,"k":[{"o":{"x":0.333,"y":0},"i":{"x":0.667,"y":1},"s":[103.6,172.96,0],"t":12,"ti":[-49.707,-49.92,0],"to":[49.707,49.92,0]},{"s":[401.84,472.48,0],"t":42}],"ix":2},"r":{"a":0,"k":45,"ix":10},"sa":{"a":0,"k":0},"o":{"a":0,"k":68,"ix":11}},"ef":[],"shapes":[{"ty":"gr","bm":0,"hd":false,"mn":"ADBE Vector Group","nm":"Rectángulo 1","ix":1,"cix":2,"np":3,"it":[{"ty":"rc","bm":0,"hd":false,"mn":"ADBE Vector Shape - Rect","nm":"Trazado de rectángulo 1","d":1,"p":{"a":0,"k":[0,0],"ix":3},"r":{"a":0,"k":0,"ix":4},"s":{"a":0,"k":[136,706],"ix":2}},{"ty":"fl","bm":0,"hd":false,"mn":"ADBE Vector Graphic - Fill","nm":"Relleno 1","c":{"a":0,"k":[1,1,1],"ix":4},"r":1,"o":{"a":0,"k":100,"ix":5}},{"ty":"tr","a":{"a":0,"k":[0,0],"ix":1},"s":{"a":0,"k":[100,100],"ix":3},"sk":{"a":0,"k":0,"ix":4},"p":{"a":0,"k":[-62,125],"ix":2},"r":{"a":0,"k":0,"ix":6},"sa":{"a":0,"k":0,"ix":5},"o":{"a":0,"k":100,"ix":7}}]}],"ind":5},{"ty":4,"nm":"estrella contornos","sr":1,"st":0,"op":1500,"ip":0,"hd":false,"ddd":0,"bm":0,"hasMask":false,"ao":0,"ks":{"a":{"a":0,"k":[116.953,111.242,0],"ix":1},"s":{"a":0,"k":[64,64,100],"ix":6},"sk":{"a":0,"k":0},"p":{"a":0,"k":[251.667,318.426,0],"ix":2},"r":{"a":0,"k":0,"ix":10},"sa":{"a":0,"k":0},"o":{"a":0,"k":100,"ix":11}},"ef":[],"shapes":[{"ty":"gr","bm":0,"hd":false,"mn":"ADBE Vector Group","nm":"Grupo 1","ix":1,"cix":2,"np":2,"it":[{"ty":"sh","bm":0,"hd":false,"mn":"ADBE Vector Shape - Group","nm":"Trazado 1","ix":1,"d":1,"ks":{"a":0,"k":{"c":true,"i":[[1.665,-3.373],[0,0],[1.478,-0.214],[0,0],[-2.693,-2.625],[0,0],[0.252,-1.472],[0,0],[-3.329,1.75],[0,0],[-1.322,-0.695],[0,0],[0.636,3.707],[0,0],[-1.069,1.043],[0,0],[3.722,0.54],[0,0],[0.661,1.339],[0,0]],"o":[[0,0],[-0.661,1.339],[0,0],[-3.722,0.54],[0,0],[1.069,1.043],[0,0],[-0.636,3.707],[0,0],[1.322,-0.695],[0,0],[3.33,1.75],[0,0],[-0.252,-1.472],[0,0],[2.693,-2.625],[0,0],[-1.478,-0.214],[0,0],[-1.665,-3.373]],"v":[[-4.069,-107.619],[-36.211,-42.495],[-39.626,-40.013],[-111.495,-29.569],[-114.01,-21.829],[-62.005,28.863],[-60.701,32.88],[-72.977,104.458],[-66.393,109.242],[-2.112,75.447],[2.112,75.447],[66.393,109.242],[72.978,104.458],[60.701,32.88],[62.005,28.863],[114.01,-21.829],[111.495,-29.569],[39.627,-40.013],[36.21,-42.495],[4.07,-107.619]]},"ix":2}},{"ty":"fl","bm":0,"hd":false,"mn":"ADBE Vector Graphic - Fill","nm":"Relleno 1","c":{"a":0,"k":[0.8588,0.5412,0.1569],"ix":4},"r":1,"o":{"a":0,"k":100,"ix":5}},{"ty":"tr","a":{"a":0,"k":[0,0],"ix":1},"s":{"a":0,"k":[100,100],"ix":3},"sk":{"a":0,"k":0,"ix":4},"p":{"a":0,"k":[116.953,111.242],"ix":2},"r":{"a":0,"k":0,"ix":6},"sa":{"a":0,"k":0,"ix":5},"o":{"a":0,"k":100,"ix":7}}]}],"ind":6}]}]}